polar_patch/__cli__.py
polar_patch/__init__.py
polar_patch/_version.py
polar_patch/merge_lockfiles.py
polar_patch/test_func_form.py
polar_patch/test_func_form_classes.py
polar_patch/ast/plugin_visitor.py
polar_patch/ast/pp_transformer.py
polar_patch/ast/providers/has_type_checking_block.py
polar_patch/ast/providers/polars_class_provider.py
polar_patch/models/lockfile_entry.py
polar_patch/models/plugin.py
polar_patch/schemas/polars_classes.py
polar_patch/schemas/toml_schema.py
polar_patch/templates/plugin_imports.py.j2
polar_patch-0.0.9.dist-info/METADATA
polar_patch-0.0.9.dist-info/WHEEL
polar_patch-0.0.9.dist-info/entry_points.txt
polar_patch-0.0.9.dist-info/licenses/LICENSE
polar_patch-0.0.9.dist-info/RECORD
