Metadata-Version: 2.3
Name: polar_patch
Version: 0.0.9
Summary: A tool that brings type safety and type checking enhancements to the Polars library.
Author: Jeremy Meek
License-File: LICENSE
Requires-Python: <3.13,>=3.12
Requires-Dist: aiofiles==24.1.0
Requires-Dist: jinja2==3.1.4
Requires-Dist: libcst==1.4.0
Requires-Dist: pydantic==2.8.2
Requires-Dist: pywatchman==2.0.0
Requires-Dist: toml==0.10.2
Requires-Dist: typer==0.12.5
